goe_prometheus/__init__.py
goe_prometheus/__main__.py
goe_prometheus/charger.py
goe_prometheus/common.py
goe_prometheus/config.py
goe_prometheus/controller.py
goe_prometheus/util.py
goe_prometheus-0.2.2.dist-info/METADATA
goe_prometheus-0.2.2.dist-info/WHEEL
goe_prometheus-0.2.2.dist-info/entry_points.txt
goe_prometheus-0.2.2.dist-info/RECORD
